my_apis/__init__.py
my_apis/main.py
my_apis-0.1.0.dist-info/METADATA
my_apis-0.1.0.dist-info/WHEEL
my_apis-0.1.0.dist-info/top_level.txt
my_apis-0.1.0.dist-info/RECORD
