Metadata-Version: 2.2
Name: my_apis
Version: 0.1.0
Requires-Dist: pandas
Requires-Dist: openai
Requires-Dist: requests
Dynamic: description
Dynamic: description-content-type
Dynamic: requires-dist
